{
    "family": "cci-task3",
    "executionRoleArn":  arn:aws:iam::014901580825:role/ecsTaskExecutionRole
    "containerDefinitions": [
        {
            "name": "cci-task3",
            "image": "317367993082.dkr.ecr.ap-southeast-2.amazonaws.com/cci-repos2:latest",
            "cpu": 1024,
            "memoryReservation": 1024,
            "portMappings": [
              {
                    "containerPort": 3001,
                    "hostPort": 80,
                    "protocol": "tcp"
              }
            ],
            "command": [
                "./main"
            ],
            "essential": true
        }
    ]
}
